Metadata-Version: 2.1
Name: TenserNet
Version: 1.0.0
Summary: This Module is Just for Holding Package Name For Now
Home-page: 
Author: Parth Patel
Author-email: TenserNet@gmail.com
License: MIT
Keywords: This Module is Just for Holding Package Name For Now
License-File: Licence.txt.txt
